mlsconverters/__init__.py
mlsconverters/common.py
mlsconverters/decorators.py
mlsconverters/io.py
mlsconverters/keras.py
mlsconverters/models.py
mlsconverters/session.py
mlsconverters/sklearn.py
mlsconverters/xgboost.py
tests/__init__.py
tests/test_keras.py
tests/test_model.py
mlschema_converters-0.1.2.dist-info/LICENSE
mlschema_converters-0.1.2.dist-info/METADATA
mlschema_converters-0.1.2.dist-info/WHEEL
mlschema_converters-0.1.2.dist-info/top_level.txt
mlschema_converters-0.1.2.dist-info/RECORD
